{
  "source_file": "7.jpg",
  "ocr_summary": {
    "variant_used": "binary",
    "token_count": 54,
    "line_count": 36,
    "mean_confidence": 0.9664,
    "variant_score": 0.8253
  },
  "store_name": {
    "value": "Walmart",
    "confidence": 0.9035,
    "raw_text": "Walmart"
  },
  "date": {
    "value": "2017-11-13",
    "confidence": 0.8984,
    "raw_text": "11/13/17 12:34:04"
  },
  "items": [
    {
      "name": "6 WING PLATE",
      "price": "3.98",
      "confidence": 0.8817,
      "raw_text": "6 WING PLATE 020108870398 :3.98 P"
    },
    {
      "name": "CUTIE CAR",
      "price": "12.88",
      "confidence": 0.9184,
      "raw_text": "CUTIE CAR 063099656644 12.88"
    }
  ],
  "items_confidence": 0.9001,
  "total_amount": {
    "value": "23.19",
    "confidence": 0.99,
    "raw_text": "TOTAL. 23.19"
  },
  "low_confidence_fields": [],
  "conflicts": [],
  "notes": []
}