{
  "source_file": "X51005711454.jpg",
  "ocr_summary": {
    "variant_used": "original",
    "token_count": 56,
    "line_count": 32,
    "mean_confidence": 0.971,
    "variant_score": 0.867
  },
  "store_name": {
    "value": "JALANTEMENGGUNG23/9",
    "confidence": 0.99,
    "raw_text": "JALANTEMENGGUNG23/9"
  },
  "date": {
    "value": null,
    "confidence": 0.0,
    "raw_text": null
  },
  "items": [
    {
      "name": "PappaRich BmC",
      "price": "0.19",
      "confidence": 0.8723,
      "raw_text": "PappaRich BmC || NO.19&21"
    },
    {
      "name": "1 D 28 MILODINO(I)E",
      "price": "7.45",
      "confidence": 0.8827,
      "raw_text": "1 D28MILODINO(I)E 7.45 S"
    },
    {
      "name": "2 R 03 N'LEMAK+fcE",
      "price": "35.66",
      "confidence": 0.9006,
      "raw_text": "2 R03 N'LEMAK+fcE@17.83 35.66 S"
    },
    {
      "name": "1 N 22 SPRG NDL+SU+CrE",
      "price": "9.34",
      "confidence": 0.9138,
      "raw_text": "1 N22 SPRG NDL+SU+CrE 9.34S"
    },
    {
      "name": "BO 2 HALF BLEGG E",
      "price": "4.53",
      "confidence": 0.8947,
      "raw_text": "BO2HALF BLEGG E 4.53S"
    },
    {
      "name": "D 19 CHAM(I)E",
      "price": "5.57",
      "confidence": 0.8808,
      "raw_text": "D19 CHAM（I）E 5.57S"
    },
    {
      "name": "10%SrvChg",
      "price": "6.25",
      "confidence": 0.9269,
      "raw_text": "10%SrvChg 6.25"
    },
    {
      "name": "6%GST",
      "price": "4.13",
      "confidence": 0.9281,
      "raw_text": "6%GST 4.13"
    }
  ],
  "items_confidence": 0.9,
  "total_amount": {
    "value": "72.93",
    "confidence": 0.99,
    "raw_text": "Total: 72.93"
  },
  "low_confidence_fields": [
    "date"
  ],
  "conflicts": [],
  "notes": []
}