{
  "source_file": "X51005447841.jpg",
  "ocr_summary": {
    "variant_used": "enhanced",
    "token_count": 60,
    "line_count": 31,
    "mean_confidence": 0.9777,
    "variant_score": 0.9048
  },
  "store_name": {
    "value": "PASARAYA BORONG PINTAR",
    "confidence": 0.99,
    "raw_text": "PASARAYA BORONG PINTAR"
  },
  "date": {
    "value": null,
    "confidence": 0.0,
    "raw_text": null
  },
  "items": [
    {
      "name": "1 WALK",
      "price": "1.20",
      "confidence": 0.9179,
      "raw_text": "1 WALK 1.20 1.20 1.20 ZRL"
    },
    {
      "name": "1 WALK",
      "price": "1.90",
      "confidence": 0.9148,
      "raw_text": "1 WALK 1.90 1.90 1.90 ZRL"
    },
    {
      "name": "1 WALK",
      "price": "2.70",
      "confidence": 0.9125,
      "raw_text": "1 WALK 2.70 2.70 2.70 ZRL"
    },
    {
      "name": "1 WALK",
      "price": "4.60",
      "confidence": 0.9234,
      "raw_text": "1 WALK 4.60 4.60 4.60 ZRL"
    }
  ],
  "items_confidence": 0.9172,
  "total_amount": {
    "value": "10.40",
    "confidence": 0.99,
    "raw_text": "Total Includes GST O% 10.40"
  },
  "low_confidence_fields": [
    "date"
  ],
  "conflicts": [],
  "notes": []
}