{
  "source_file": "X51005705722.jpg",
  "ocr_summary": {
    "variant_used": "enhanced",
    "token_count": 57,
    "line_count": 31,
    "mean_confidence": 0.9742,
    "variant_score": 0.8834
  },
  "store_name": {
    "value": "ASO ELECTRICAL TRADING SDN BHD",
    "confidence": 0.99,
    "raw_text": "ASO ELECTRICAL TRADING SDN BHD"
  },
  "date": {
    "value": "2017-09-27",
    "confidence": 0.99,
    "raw_text": "Receipt#:CS00087400 Date: 27/09/2017"
  },
  "items": [
    {
      "name": "TOT QTY",
      "price": "248.04",
      "confidence": 0.9087,
      "raw_text": "TOT QTY: 3 248.04"
    },
    {
      "name": "(Excluded GST) Sub Total",
      "price": "234.00",
      "confidence": 0.9221,
      "raw_text": "(Excluded GST) Sub Total : 234.00"
    },
    {
      "name": "Rounding",
      "price": "0.01",
      "confidence": 0.9176,
      "raw_text": "Rounding 0.01"
    }
  ],
  "items_confidence": 0.9162,
  "total_amount": {
    "value": "14.04",
    "confidence": 0.99,
    "raw_text": "Total: 234.00 14.04"
  },
  "low_confidence_fields": [],
  "conflicts": [
    "Competing total candidate 248.05 from 'Total : 248.05'"
  ],
  "notes": []
}